Workbook
Name a: Sheet1!$XBP$1
Name total: Sheet1!$D$12
Name total: Sheet1!$D$12
Name Year_email_total: Sheet1!$B$14
Name Year_SR: Sheet1!$C$14

Sheet Sheet1
A1: Month | B1: Email Respondents | C1: Satisfied Respondents | D1: Monthly Revenue | E1: Monthly Cost
A2: Jan | B2: 125 | C2: 85 | D2: 12000 | E2: 8000
A3: Feb | B3: 140 | C3: 98 | D3: 13500 | E3: 8500 | F3: Using Conditional Formatting to spot missing or unfilled data
A4: Mar | B4: 130 | C4: 88 | D4: 12800 | E4: 8200
A5: Apr | B5: 150 | C5: 105 | D5: 14500 | E5: 9000
A6: May | B6: 160 | D6: 15000 | E6: 9400
A7: Dec | B7: 170 | C7: 119 | D7: 15800 | E7: 9800 | G7: =IF(ISBLANK(C6),0,C6) -> 0
A8: Jul | B8: 165 | C8: 116 | D8: 15400 | E8: 9600
A9: Aug | B9: 175 | C9: 123 | D9: 16200 | E9: 10000
A10: Sep | B10: 180 | C10: 126 | D10: 16800 | E10: 10300
A11: Oct | B11: 190 | C11: 133 | D11: 17500 | E11: 10700
A12: Nov | B12: 200 | C12: 140 | D12: 18200 | E12: 11100
A13: Dec | B13: 210 | C13: 147 | D13: 19000 | E13: 11600
A14: Year Sum | B14: =SUM(B2:B13) -> 1995 | C14: =SUM(C2:C13) -> 1280 | D14: =SUM(D2:D13) -> 138300 | E14: =SUM(E2:E13) -> 116200
A15: Year Average | B15: =AVERAGE(B1:B2) -> 125 | C15: =AVERAGE(C2:C13) -> 116.36364 | D15: =AVERAGE(D2:D13) -> 15366.667 | E15: =AVERAGE(E2:E13) -> 9683.3333
A18: Product | B18: Quantity Sold | C18: Unit Price | D18: Total Revenue
A19: A | B19: 10 | C19: 5.99 | D19: =B19*C19 -> 59.9
A20: B | B20: 15 | C20: 7.49 | D20: =B20*C20 -> 112.35
A21: C | B21: 8 | C21: 12.99 | D21: =B21*C21 -> 103.92
A22: D | B22: 25 | C22: 4.75 | D22: =B22*C22 -> 118.75
A23: E | B23: 5 | C23: 19.99 | D23: =B23*C23 -> 99.95
A24: Total | B24: =SUM(B19:B23) -> 63

Sheet Sheet2
A1: Date | B1: Store | C1: Title | D1: Author | E1: Units Sold | F1: Price
A2: 45445 | B2: Downtown | C2: Mindful Moments | D2: Sara Patel | E2: 40 | F2: 10
A3: 45444 | B3: Downtown | C3: The Silent Library | D3: Jane Abbott | E3: 32 | F3: 12.99
A4: 45445 | B4: Downtown | C4: The Dusk Pact | D4: Ava Moreno | E4: 27 | F4: 14.25
A5: 45446 | B5: Downtown | C5: Productivity Unlocked | D5: James Yu | E5: 22 | F5: 11.75
A6: 45444 | B6: Downtown | C6: Code of the Ancients | D6: Leo Zhang | E6: 18 | F6: 15.5

Sheet Sheet3
A1: First Name | B1: Last Name | C1: Location | D1: Rating | E1: Using "Proper" Formula | F1: Using "Left" and "Find Formula
A2: Alice | B2: Smith | C2: New York | D2: 4.1 | E2: =PROPER(CONCATENATE(A2," ",B2,)) -> Alice Smith | F2: =LEFT(C2,FIND(" ",C2)) -> New
A3: bob | B3: johnson | C3: los angeles | D3: 3.8 | E3: =PROPER(CONCATENATE(A3," ",B3,)) -> Bob Johnson | F3: =LEFT(C3,FIND(" ",C3)) -> los
A4: CLARA | B4: LI | C4: SAN FRANCISCO | D4: 4.6 | E4: =PROPER(CONCATENATE(A4," ",B4,)) -> Clara Li | F4: =LEFT(C4,FIND(" ",C4)) -> SAN
A5: Daniel | B5: Rivera | C5: Rio de Janeiro | D5: 4.9 | E5: =PROPER(CONCATENATE(A5," ",B5,)) -> Daniel Rivera | F5: =LEFT(C5,FIND(" ",C5)) -> Rio
A6: Elena | B6: murphy | C6: san Juan | D6: 3.7 | E6: =PROPER(CONCATENATE(A6," ",B6,)) -> Elena Murphy | F6: =LEFT(C6,FIND(" ",C6)) -> san
C7: Average | D7: =AVERAGE(D2,D3,D4,D5,D6) -> 4.22
C8: Rounded Average | D8: =ROUND(D7,1) -> 4.2
A11: First Name | B11: Last Name | C11: City | D11: State | E11: Using "Concatenate" Formula | F11: Using "Trim" Formula
A12: Ava | B12: Johnson | C12: Dallas | D12: TX | E12: =CONCATENATE(A12," ",B12," "," lives in"," ",C12) -> Ava Johnson lives in Dallas | F12: =TRIM(E12) -> Ava Johnson lives in Dallas
A13: Noah | B13: Smith | C13: Seattle | D13: WA | E13: =CONCATENATE(A13," ",B13," "," lives in"," ",C13) -> Noah Smith lives in Seattle | F13: =TRIM(E13) -> Noah Smith lives in Seattle
A14: Mia | B14: Brown | C14: Chicago | D14: IL | E14: =CONCATENATE(A14," ",B14," "," lives in"," ",C14) -> Mia Brown lives in Chicago | F14: =TRIM(E14) -> Mia Brown lives in Chicago
A15: Liam | B15: Davis | C15: Atlanta | D15: GA | E15: =CONCATENATE(A15," ",B15," "," lives in"," ",C15) -> Liam Davis lives in Atlanta | F15: =TRIM(E15) -> Liam Davis lives in Atlanta
A16: Emma | B16: Wilson | C16: Denver | D16: CO | E16: =CONCATENATE(A16," ",B16," "," lives in"," ",C16) -> Emma Wilson lives in Denver | F16: =TRIM(E16) -> Emma Wilson lives in Denver
A17: Olivia | B17: Martin | C17: Phoenix | D17: AZ | E17: =CONCATENATE(A17," ",B17," "," lives in"," ",C17) -> Olivia Martin lives in Phoenix | F17: =TRIM(E17) -> Olivia Martin lives in Phoenix
A18: Elijah | B18: Clark | C18: Boston | D18: MA | E18: =CONCATENATE(A18," ",B18," "," lives in"," ",C18) -> Elijah Clark lives in Boston | F18: =TRIM(E18) -> Elijah Clark lives in Boston
A19: Sophia | B19: Lewis | C19: Miami | D19: FL | E19: =CONCATENATE(A19," ",B19," "," lives in"," ",C19) -> Sophia Lewis lives in Miami | F19: =TRIM(E19) -> Sophia Lewis lives in Miami
A20: James | B20: Walker | C20: Austin | D20: TX | E20: =CONCATENATE(A20," ",B20," "," lives in"," ",C20) -> James Walker lives in Austin | F20: =TRIM(E20) -> James Walker lives in Austin
A21: Isabella | B21: Hall | C21: Portland | D21: OR | E21: =CONCATENATE(A21," ",B21," "," lives in"," ",C21) -> Isabella Hall lives in Portland | F21: =TRIM(E21) -> Isabella Hall lives in Portland

Sheet Sheet4
A1: Employee | B1: Hours Worked | C1: Tasks Completed | D1: Finding top proformer by "If" and "and" formula
A2: Alice | B2: 42 | C2: 8 | D2: =IF(AND(B2>40,C2>8), "Yes", "") | E2: =IF(AND(B2>40,C2>8),"yes"," ")
A3: Ben | B3: 36 | C3: 5 | D3: =IF(AND(B3>40, C3>8), "Yes", "") | E3: =IF(AND(B3>40,C3>8),"yes"," ")
A4: Carla | B4: 45 | C4: 10 | D4: =IF(AND(B4>40, C4>8), "Yes", "") -> Yes
A5: Dan | B5: 30 | C5: 4 | D5: =IF(AND(B5>40, C5>8), "Yes", "")
A6: Eva | C6: 6 | D6: =IF(AND(B6>40, C6>8), "Yes", "")
A7: Felix | B7: 50 | C7: 12 | D7: =IF(AND(B7>40, C7>8), "Yes", "") -> Yes
A8: Grace | B8: 38 | C8: 6 | D8: =IF(AND(B8>40, C8>8), "Yes", "")
A9: Hugo | B9: 40 | D9: =IF(AND(B9>40, C9>8), "Yes", "")
A10: Iris | B10: 44 | C10: 9 | D10: =IF(AND(B10>40, C10>8), "Yes", "") -> Yes
A11: Jake | B11: 29 | C11: 3 | D11: =IF(AND(B11>40, C11>8), "Yes", "")
A12: Average | B12: =AVERAGE(B2:B11) -> 39.333333 | C12: =AVERAGE(C2:C11) -> 7
A13: Max | B13: =MAX(B2:B11) -> 50 | C13: =MAX(C2:C11) -> 12 | D13: Using Conditional Formatting to spot above 8 tasks completed
A14: Using "IF" and "Isblank" | B14: =IF(ISBLANK(B6),40,B6) -> 40 | D14: Using Conditional Formatting to spot missing or unfilled data
F16: Using "Texts to Columns"
A17: Event | B17: Date | C17: Year | D17: Month | E17: Day | F17: Coordinator first name | G17: Last Name
A18: Spring Festival | B18: 45757 | C18: =YEAR(B18) -> 2025 | D18: =MONTH(B18) -> 4 | E18: =DAY(B18) -> 10 | F18: Yamada | G18: Keiko
A19: Summer Kickoff | B19: 45828 | C19: =YEAR(B19) -> 2025 | D19: =MONTH(B19) -> 6 | E19: =DAY(B19) -> 20 | F19: Ito | G19: Daichi
A20: Fall Mixer | B20: 45935 | C20: =YEAR(B20) -> 2025 | D20: =MONTH(B20) -> 10 | E20: =DAY(B20) -> 5 | F20: Yamada | G20: Keiko
A21: Winter Wrap-Up | B21: 46006 | C21: =YEAR(B21) -> 2025 | D21: =MONTH(B21) -> 12 | E21: =DAY(B21) -> 15 | F21: Tanaka | G21: Ayumi

Sheet Employee Data
A1: Employee ID | B1: Name | C1: Dept Code | D1: Level | E1: Salary | F1: Deparment Name Using "Vlookup"
A2: 101 | B2: Alice Park | C2: MKT | D2: Mid | E2: 65000 | F2: =VLOOKUP(C2,'Dept Code Refs'!A:B,2,FALSE) -> Marketing
A3: 102 | B3: Brian Lee | C3: ENG | D3: Senior | E3: 95000 | F3: =VLOOKUP(C3,'Dept Code Refs'!A:B,2,FALSE) -> Engineering
A4: 103 | B4: Carla Diaz | C4: MKT | D4: Entry | E4: 42000 | F4: =VLOOKUP(C4,'Dept Code Refs'!A:B,2,FALSE) -> Marketing
A5: 104 | B5: Daniel Cho | C5: HR | D5: Mid | E5: 58000 | F5: =VLOOKUP(C5,'Dept Code Refs'!A:B,2,FALSE) -> Human Resources
A6: 105 | B6: Eva Patel | C6: ENG | D6: Entry | E6: 50000 | F6: =VLOOKUP(C6,'Dept Code Refs'!A:B,2,FALSE) -> Engineering
A7: 106 | B7: Fiona Zhang | C7: HR | D7: Executive | E7: 120000 | F7: =VLOOKUP(C7,'Dept Code Refs'!A:B,2,FALSE) -> Human Resources
A8: 107 | B8: George Kim | C8: ENG | D8: Mid | E8: 72000 | F8: =VLOOKUP(C8,'Dept Code Refs'!A:B,2,FALSE) -> Engineering
A9: 108 | B9: Hannah Li | C9: MKT | D9: Senior | E9: 88000 | F9: =VLOOKUP(C9,'Dept Code Refs'!A:B,2,FALSE) -> Marketing

Sheet Dept Code Refs
A1: Dept Code | B1: Department Name
A2: MKT | B2: Marketing
A3: ENG | B3: Engineering
A4: HR | B4: Human Resources

Sheet Pivot Table1
A3: Count of Employee ID | B3: Levels
A4: Department Name | B4: Entry | C4: Executive | D4: Mid | E4: Senior | F4: Grand Total
A5: Engineering | B5: 1 | D5: 1 | E5: 1 | F5: 3
A6: Human Resources | C6: 1 | D6: 1 | F6: 2
A7: Marketing | B7: 1 | D7: 1 | E7: 1 | F7: 3
A8: Grand Total | B8: 2 | C8: 1 | D8: 3 | E8: 2 | F8: 8

Sheet Pivot Table2
A3: Sum of Salary | B3: Departments
A4: Level | B4: Engineering | C4: Human Resources | D4: Marketing | E4: Grand Total
A5: Entry | B5: 50000 | D5: 42000 | E5: 92000
A6: Executive | C6: 120000 | E6: 120000
A7: Mid | B7: 72000 | C7: 58000 | D7: 65000 | E7: 195000
A8: Senior | B8: 95000 | D8: 88000 | E8: 183000
A9: Grand Total | B9: 217000 | C9: 178000 | D9: 195000 | E9: 590000
